{
  "title": "Lab 6.3: 🔒 Le Gardien des Accès (chmod & umask)",
  "description": "Apprenez à modifier les permissions, à utiliser les droits spéciaux et à configurer umask.",
  "backend": {
    "imageid": "ubuntu",
    "user": "learner"
  },
  "details": {
    "intro": {
      "text": "intro.md",
      "background": "background.sh",
      "foreground": "foreground.sh"
    },
    "steps": [
      {
        "title": "Sculpter les Droits : Le Langage Symbolique (+, -, =)",
        "text": "step1/text.md",
        "verify": "step1/verify.sh"
      },
      {
        "title": "Le Code Maître : La Puissance de l'Octal (755, 600)",
        "text": "step2/text.md",
        "verify": "step2/verify.sh"
      },
      {
        "title": "L'Emprunt d'Identité : Le Super-Pouvoir du SUID",
        "text": "step3/text.md",
        "verify": "step3/verify.sh"
      },
      {
        "title": "La Salle du Conseil (SGID) et le Coffre-Fort Public (Sticky Bit)",
        "text": "step4/text.md",
        "verify": "step4/verify.sh"
      },
      {
        "title": "La Règle du Gardien : Maîtriser `umask`",
        "text": "step5/text.md",
        "verify": "step5/verify.sh"
      }
    ],
    "finish": {
      "text": "finish.md"
    }
  }
}